esrgan_video_enhance/__init__.py
esrgan_video_enhance/inference_realesrgan_video.py
esrgan_video_enhance/version.py
esrganenhance/__init__.py
esrganenhance/inference_realesrgan_video.py
esrganenhance/version.py
realesrgan/__init__.py
realesrgan/train.py
realesrgan/utils.py
realesrgan/version.py
realesrgan/archs/__init__.py
realesrgan/archs/discriminator_arch.py
realesrgan/archs/srvgg_arch.py
realesrgan/data/__init__.py
realesrgan/data/realesrgan_dataset.py
realesrgan/data/realesrgan_paired_dataset.py
realesrgan/models/__init__.py
realesrgan/models/realesrgan_model.py
realesrgan/models/realesrnet_model.py
video_enhance/__init__.py
video_enhance/inference_realesrgan_video.py
esrganenhance-0.4.1.dist-info/LICENSE
esrganenhance-0.4.1.dist-info/METADATA
esrganenhance-0.4.1.dist-info/WHEEL
esrganenhance-0.4.1.dist-info/top_level.txt
esrganenhance-0.4.1.dist-info/RECORD
