Metadata-Version: 2.1
Name: esrganenhance
Version: 0.4.1
Summary: Real-ESRGAN aims at developing Practical Algorithms for General Image Restoration
Home-page: https://github.com/loongcat-mega/Real-ESRGAN.git
Author: qingruixu
Author-email: qingruixu@tencent.com
License: BSD-3-Clause License
Keywords: computer vision,pytorch,image restoration,super-resolution,esrgan,real-esrgan
Classifier: Development Status :: 4 - Beta
Classifier: License :: OSI Approved :: Apache Software License
Classifier: Operating System :: OS Independent
Classifier: Programming Language :: Python :: 3
Classifier: Programming Language :: Python :: 3.7
Classifier: Programming Language :: Python :: 3.8
License-File: LICENSE
Requires-Dist: basicsr >=1.4.2
Requires-Dist: facexlib >=0.2.5
Requires-Dist: gfpgan >=1.3.5
Requires-Dist: numpy
Requires-Dist: Pillow
Requires-Dist: torch >=1.7
Requires-Dist: torchvision
Requires-Dist: tqdm
